setup.cfg
setup.py
src/agnos/__init__.py
src/agnos/httptransport.py
src/agnos/packers.py
src/agnos/protocol.py
src/agnos/servers.py
src/agnos/transports.py
src/agnos/utils.py
src/agnos/version.py
src/agnos/restful/__init__.py
src/agnos/restful/jsonser.py
src/agnos/restful/server.py
src/agnos/restful/util.py
src/agnos/restful/xmlser.py
src/libagnos.egg-info/PKG-INFO
src/libagnos.egg-info/SOURCES.txt
src/libagnos.egg-info/dependency_links.txt
src/libagnos.egg-info/top_level.txt