Metadata-Version: 1.0
Name: libagnos
Version: 1.0.1
Summary: Agnos Python Libraries
Home-page: http://agnos.sourceforge.net
Author: Tomer Filiba
Author-email: tomerf@il.ibm.com
License: Apache License 2.0
Download-URL: http://www.sourceforge.net/projects/agnos/files/1.0.1
Platform: POSIX
Platform: Windows
